bioreader/__init__.py
bioreader/_core.py
bioreader/lookup/__init__.py
bioreader/lookup/_core.py
bioreader-0.0.4.dist-info/LICENSE
bioreader-0.0.4.dist-info/WHEEL
bioreader-0.0.4.dist-info/METADATA
bioreader-0.0.4.dist-info/RECORD
