Metadata-Version: 2.1
Name: bioreader
Version: 0.0.4
Summary: Bio file readers, instrument schema.
Author-email: Lamin Labs <laminlabs@gmail.com>
Requires-Dist: nbproject
Requires-Dist: pre-commit ; extra == "dev"
Requires-Dist: nox ; extra == "dev"
Requires-Dist: pytest>=6.0 ; extra == "test"
Requires-Dist: pytest-cov ; extra == "test"
Project-URL: Home, https://github.com/laminlabs/bioreader
Provides-Extra: dev
Provides-Extra: test
